fittytestpypi/__init__.py
fittytestpypi/__main__.py
fittytestpypi/billi.txt
fittytestpypi/cli.py
fittytestpypi-1.15.dist-info/METADATA
fittytestpypi-1.15.dist-info/WHEEL
fittytestpypi-1.15.dist-info/entry_points.txt
fittytestpypi-1.15.dist-info/top_level.txt
fittytestpypi-1.15.dist-info/RECORD
