Metadata-Version: 2.1
Name: fittytestpypi
Version: 1.15
Summary: myshortdesc
Home-page: https://github.com/fittytizio/testpypi
Author: fittytizio
License: MIT
Keywords: fittytestpypi testpypi
Classifier: Intended Audience :: End Users/Desktop
Classifier: Environment :: Console
Classifier: Natural Language :: English
Classifier: License :: OSI Approved :: MIT License
Classifier: Programming Language :: Python
Classifier: Programming Language :: Python :: 3
Classifier: Programming Language :: Python :: 3 :: Only
Classifier: Programming Language :: Python :: 3.9
Classifier: Topic :: Terminals
Classifier: Topic :: Utilities
Requires-Python: >=3.9.1
Requires-Dist: PyYAML (>=5.4.1)
